_solib_k8/_U_S_Sunitree_Scyclonedds_Cshared_Uimport_Uddsc___Uunitree_Scyclonedds_Slib_Sx86_U64/libddsc.so.0
_solib_k8/_U_S_Sunitree_Scyclonedds_Cshared_Uimport_Uddscxx___Uunitree_Scyclonedds_Slib_Sx86_U64/libddscxx.so.0
pybind11_abseil/status.so
unitree_api_bindings/unitree_api.so
unitree_go2_api-0.0.24.dist-info/WHEEL
unitree_go2_api-0.0.24.dist-info/METADATA
unitree_go2_api-0.0.24.dist-info/RECORD
